jsacm/__init__.py
jsacm/jsacm.py
jsacm/nggup.mp4
jsacm/test.py
jsacm-0.3.0.dist-info/METADATA
jsacm-0.3.0.dist-info/WHEEL
jsacm-0.3.0.dist-info/top_level.txt
jsacm-0.3.0.dist-info/RECORD
