Metadata-Version: 2.1
Name: jsacm
Version: 0.3.0
Summary: A python package to aid in programming (calculator credit to Oliver)
Author: Jacob Browning
Author-email: <jacobbrowning2008@gmail.com>
Keywords: python
Classifier: Development Status :: 3 - Alpha
Classifier: Intended Audience :: Education
Classifier: Programming Language :: Python :: 2
Classifier: Programming Language :: Python :: 3
Classifier: Operating System :: MacOS :: MacOS X
Classifier: Operating System :: Microsoft :: Windows
Requires-Dist: aspose.words
Requires-Dist: datetime
Requires-Dist: deep-translator
Requires-Dist: names
Requires-Dist: pytubefix
Requires-Dist: tqdm
